{
    "id": 108987989,
    "name": "Grumble Rumble",
    "author": "Eli",
    "creators": ["Eli", "Ben"],
    "verifier": "Ben",
    "verification": "https://youtu.be/mAJhtkVjl-g",
    "percentToQualify": "35",
    "password": "Free To Copy",
    "records": [
          {
            "user": "Eli",
            "link": "linkplaceholder",
            "percent": 100,
            "hz": 75
        },
          {
            "user": "Leo",
            "link": "linkplaceholder",
            "percent": 100,
            "hz": 144
        }
    ]
}
